[
  {
    "name": "Paleo Pecan Maple Salmon",
    "description": "Paleo, gluten-free and dairy-free!."
   
  },
  {
    "name": "The Ultimate Tech Quiz",
    "description": "A web app that will give users 10 new technical questions each day and track their progress in things like programming, cybersecurity, database architecture, and more!"
   
  },
  {
    "name": "Roll 'Em Up",
    "description": "A game for Windows and macOS where players move a ball through a series of increasingly challenging mazes."
    
  }
]
https://imagesvc.meredithcorp.io/v3/mm/image?url=https%3A%2F%2Fimages.media-allrecipes.com%2Fuserphotos%2F8716309.jpg&q=85